pixrypt_python-1.0.0.data/data/my_data/data_file
pixrypt_python-1.0.0.dist-info/DESCRIPTION.rst
pixrypt_python-1.0.0.dist-info/METADATA
pixrypt_python-1.0.0.dist-info/RECORD
pixrypt_python-1.0.0.dist-info/WHEEL
pixrypt_python-1.0.0.dist-info/entry_points.txt
pixrypt_python-1.0.0.dist-info/metadata.json
pixrypt_python-1.0.0.dist-info/top_level.txt
source/__init__.py
source/package_data.dat
source/decoder/__init__.py
source/decoder/decoder.py
source/encoder/__init__.py
source/encoder/encoder.py
