Metadata-Version: 2.0
Name: pixrypt-python
Version: 1.0.0
Summary: Pixrypt Text-Pixel Encoding/Decoding Backend
Home-page: http://www.pixrypt.com
Author: Shaunak Raha
Author-email: shaunakraha@gmail.com
License: UNKNOWN
Keywords: pixrypt encryption development
Platform: UNKNOWN
Classifier: Development Status :: 3 - Alpha
Classifier: Intended Audience :: Developers
Classifier: Topic :: Software Development :: Build Tools
Classifier: License :: Free for non-commercial use
Classifier: Programming Language :: Python :: 2
Classifier: Programming Language :: Python :: 2.7
Classifier: Programming Language :: Python :: 3
Classifier: Programming Language :: Python :: 3.4
Classifier: Programming Language :: Python :: 3.5
Classifier: Programming Language :: Python :: 3.6
Requires-Dist: pillow
Provides-Extra: dev
Requires-Dist: check-manifest; extra == 'dev'
Provides-Extra: test
Requires-Dist: coverage; extra == 'test'
